twisted/plugins/magic_wormhole_transit_relay.py
wormhole_transit_relay/__init__.py
wormhole_transit_relay/_version.py
wormhole_transit_relay/database.py
wormhole_transit_relay/increase_rlimits.py
wormhole_transit_relay/server_state.py
wormhole_transit_relay/server_tap.py
wormhole_transit_relay/transit_server.py
wormhole_transit_relay/usage.py
wormhole_transit_relay/db-schemas/v1.sql
wormhole_transit_relay/test/__init__.py
wormhole_transit_relay/test/common.py
wormhole_transit_relay/test/test_backpressure.py
wormhole_transit_relay/test/test_config.py
wormhole_transit_relay/test/test_database.py
wormhole_transit_relay/test/test_rlimits.py
wormhole_transit_relay/test/test_service.py
wormhole_transit_relay/test/test_stats.py
wormhole_transit_relay/test/test_transit_server.py
magic_wormhole_transit_relay-0.4.0.dist-info/LICENSE
magic_wormhole_transit_relay-0.4.0.dist-info/METADATA
magic_wormhole_transit_relay-0.4.0.dist-info/WHEEL
magic_wormhole_transit_relay-0.4.0.dist-info/top_level.txt
magic_wormhole_transit_relay-0.4.0.dist-info/RECORD
